[
  {
    "address": "4 bed town house for sale Old Portsmouth, Hampshire PO1",
    "price": 799995,
    "bedrooms": 4,
    "bathrooms": 3,
    "description": "4-bed property in Portsmouth.",
    "property_url": "https://www.primelocation.com/for-sale/details/69534535/",
    "image_url": "https://lid.zoocdn.com/u/1024/768/50df80c86c5c3ce8b1396566c08a7e6687b6b221.jpg",
    "postcode": "",
    "city": "Portsmouth",
    "monthly_rent": 440,
    "annual_rent": 5280,
    "gross_yield": 0.66,
    "area_sqm": null,
    "area_estimated": false,
    "london_borough": null,
    "london_district": null,
    "postcode_district": null,
    "postcode_area": null,
    "article4_area": false,
    "article4_status": "None",
    "property_category": "residential",
    "property_type": "unknown",
    "flat_floor": null,
    "has_garden": false,
    "has_parking": false,
    "property_age": null,
    "hmo_candidate": false,
    "migrated_at": "2025-08-12T15:23:03.087304"
  },
  {
    "address": "4 bed detached house for sale Brecon Avenue, Portsmouth PO6",
    "price": 750000,
    "bedrooms": 4,
    "bathrooms": 3,
    "description": "4-bed property in Portsmouth.",
    "property_url": "https://www.primelocation.com/for-sale/details/70180773/",
    "image_url": "https://lid.zoocdn.com/u/1024/768/cbf6195816531ea67b9554d52cb9cceb47ba1e26.jpg",
    "postcode": "",
    "city": "Portsmouth",
    "monthly_rent": 440,
    "annual_rent": 5280,
    "gross_yield": 0.7,
    "area_sqm": null,
    "area_estimated": false,
    "london_borough": null,
    "london_district": null,
    "postcode_district": null,
    "postcode_area": null,
    "article4_area": false,
    "article4_status": "None",
    "property_category": "residential",
    "property_type": "unknown",
    "flat_floor": null,
    "has_garden": false,
    "has_parking": false,
    "property_age": null,
    "hmo_candidate": false,
    "migrated_at": "2025-08-12T15:23:03.087333"
  },
  {
    "address": "5 bed detached house for sale Havant Road, Farlington, Portsmouth PO6",
    "price": 950000,
    "bedrooms": 5,
    "bathrooms": 2,
    "description": "5-bed property in Portsmouth.",
    "property_url": "https://www.primelocation.com/for-sale/details/67568846/",
    "image_url": "https://lid.zoocdn.com/u/1024/768/cddfc5984a6657a547e203a0786d5fffe2acc868.jpg",
    "postcode": "",
    "city": "Portsmouth",
    "monthly_rent": 550,
    "annual_rent": 6600,
    "gross_yield": 0.69,
    "area_sqm": null,
    "area_estimated": false,
    "london_borough": null,
    "london_district": null,
    "postcode_district": null,
    "postcode_area": null,
    "article4_area": false,
    "article4_status": "None",
    "property_category": "residential",
    "property_type": "unknown",
    "flat_floor": null,
    "has_garden": false,
    "has_parking": false,
    "property_age": null,
    "hmo_candidate": false,
    "migrated_at": "2025-08-12T15:23:03.087355"
  },
  {
    "address": "5 bed detached house for sale Beverley Grove, Drayton PO6",
    "price": 1050000,
    "bedrooms": 5,
    "bathrooms": 3,
    "description": "5-bed property in Portsmouth.",
    "property_url": "https://www.primelocation.com/for-sale/details/69969276/",
    "image_url": "https://lid.zoocdn.com/u/1024/768/2fe90bf6c3fb87fea6528ee8ff9a6eba45ae2f23.jpg",
    "postcode": "",
    "city": "Portsmouth",
    "monthly_rent": 550,
    "annual_rent": 6600,
    "gross_yield": 0.63,
    "area_sqm": null,
    "area_estimated": false,
    "london_borough": null,
    "london_district": null,
    "postcode_district": null,
    "postcode_area": null,
    "article4_area": false,
    "article4_status": "None",
    "property_category": "residential",
    "property_type": "unknown",
    "flat_floor": null,
    "has_garden": false,
    "has_parking": false,
    "property_age": null,
    "hmo_candidate": false,
    "migrated_at": "2025-08-12T15:23:03.087374"
  },
  {
    "address": "4 bed town house for sale Bryher Island, Port Solent PO6",
    "price": 1295000,
    "bedrooms": 4,
    "bathrooms": 4,
    "description": "4-bed property in Portsmouth.",
    "property_url": "https://www.primelocation.com/for-sale/details/70467466/",
    "image_url": "https://lid.zoocdn.com/u/1024/768/795c7bf365d0ddc0856955459b0248ac0588be37.jpg",
    "postcode": "",
    "city": "Portsmouth",
    "monthly_rent": 440,
    "annual_rent": 5280,
    "gross_yield": 0.41,
    "area_sqm": null,
    "area_estimated": false,
    "london_borough": null,
    "london_district": null,
    "postcode_district": null,
    "postcode_area": null,
    "article4_area": false,
    "article4_status": "None",
    "property_category": "residential",
    "property_type": "unknown",
    "flat_floor": null,
    "has_garden": false,
    "has_parking": false,
    "property_age": null,
    "hmo_candidate": false,
    "migrated_at": "2025-08-12T15:23:03.087405"
  },
  {
    "address": "4 bed town house for sale Old Portsmouth, Hampshire PO1",
    "price": 1300000,
    "bedrooms": 4,
    "bathrooms": 3,
    "description": "4-bed property in Portsmouth.",
    "property_url": "https://www.primelocation.com/for-sale/details/69633367/",
    "image_url": "https://lid.zoocdn.com/u/1024/768/c651edbc174880aea46201a9a0471666fd46f3e9.jpg",
    "postcode": "",
    "city": "Portsmouth",
    "monthly_rent": 440,
    "annual_rent": 5280,
    "gross_yield": 0.41,
    "area_sqm": null,
    "area_estimated": false,
    "london_borough": null,
    "london_district": null,
    "postcode_district": null,
    "postcode_area": null,
    "article4_area": false,
    "article4_status": "None",
    "property_category": "residential",
    "property_type": "unknown",
    "flat_floor": null,
    "has_garden": false,
    "has_parking": false,
    "property_age": null,
    "hmo_candidate": false,
    "migrated_at": "2025-08-12T15:23:03.087424"
  },
  {
    "address": "3 bed end terrace house for sale Waterworks Road, Farlington, Portsmouth PO6",
    "price": 375000,
    "bedrooms": 3,
    "bathrooms": 1,
    "description": "3-bed property in Portsmouth.",
    "property_url": "https://www.primelocation.com/for-sale/details/69675515/",
    "image_url": "https://lid.zoocdn.com/u/1024/768/7473420c513a5e015543952b33d893922a744662.jpg",
    "postcode": "",
    "city": "Portsmouth",
    "monthly_rent": 330,
    "annual_rent": 3960,
    "gross_yield": 1.06,
    "area_sqm": null,
    "area_estimated": false,
    "london_borough": null,
    "london_district": null,
    "postcode_district": null,
    "postcode_area": null,
    "article4_area": false,
    "article4_status": "None",
    "property_category": "residential",
    "property_type": "unknown",
    "flat_floor": null,
    "has_garden": false,
    "has_parking": false,
    "property_age": null,
    "hmo_candidate": false,
    "migrated_at": "2025-08-12T15:23:03.087444"
  },
  {
    "address": "6 bed detached house for sale Boundary Way, Drayton PO6",
    "price": 850000,
    "bedrooms": 6,
    "bathrooms": 5,
    "description": "6-bed property in Portsmouth.",
    "property_url": "https://www.primelocation.com/for-sale/details/69977559/",
    "image_url": "https://lid.zoocdn.com/u/1024/768/50b941981380261f2e35c0c7830baf4016a39f25.jpg",
    "postcode": "",
    "city": "Portsmouth",
    "monthly_rent": 660,
    "annual_rent": 7920,
    "gross_yield": 0.93,
    "area_sqm": null,
    "area_estimated": false,
    "london_borough": null,
    "london_district": null,
    "postcode_district": null,
    "postcode_area": null,
    "article4_area": false,
    "article4_status": "None",
    "property_category": "residential",
    "property_type": "unknown",
    "flat_floor": null,
    "has_garden": false,
    "has_parking": false,
    "property_age": null,
    "hmo_candidate": false,
    "migrated_at": "2025-08-12T15:23:03.087463"
  },
  {
    "address": "5 bed detached house for sale Havant Road, Drayton, Portsmouth PO6",
    "price": 750000,
    "bedrooms": 5,
    "bathrooms": 2,
    "description": "5-bed property in Portsmouth.",
    "property_url": "https://www.primelocation.com/for-sale/details/70471918/",
    "image_url": "https://lid.zoocdn.com/u/1024/768/520f53e8ec9344faf38b623f517b77b7bb234af1.jpg",
    "postcode": "",
    "city": "Portsmouth",
    "monthly_rent": 550,
    "annual_rent": 6600,
    "gross_yield": 0.88,
    "area_sqm": null,
    "area_estimated": false,
    "london_borough": null,
    "london_district": null,
    "postcode_district": null,
    "postcode_area": null,
    "article4_area": false,
    "article4_status": "None",
    "property_category": "residential",
    "property_type": "unknown",
    "flat_floor": null,
    "has_garden": false,
    "has_parking": false,
    "property_age": null,
    "hmo_candidate": false,
    "migrated_at": "2025-08-12T15:23:03.087483"
  },
  {
    "address": "5 bed detached house for sale Beverley Grove, Portsmouth PO6",
    "price": 1000000,
    "bedrooms": 5,
    "bathrooms": 3,
    "description": "5-bed property in Portsmouth.",
    "property_url": "https://www.primelocation.com/for-sale/details/68326260/",
    "image_url": "https://lid.zoocdn.com/u/1024/768/36ba457a7fca83602d3272d23fb6d9144ebfd042.jpg",
    "postcode": "",
    "city": "Portsmouth",
    "monthly_rent": 550,
    "annual_rent": 6600,
    "gross_yield": 0.66,
    "area_sqm": null,
    "area_estimated": false,
    "london_borough": null,
    "london_district": null,
    "postcode_district": null,
    "postcode_area": null,
    "article4_area": false,
    "article4_status": "None",
    "property_category": "residential",
    "property_type": "unknown",
    "flat_floor": null,
    "has_garden": false,
    "has_parking": false,
    "property_age": null,
    "hmo_candidate": false,
    "migrated_at": "2025-08-12T15:23:03.087502"
  },
  {
    "address": "3 bed town house for sale Port Solent, Hampshire PO6",
    "price": 800000,
    "bedrooms": 3,
    "bathrooms": 3,
    "description": "3-bed property in Portsmouth.",
    "property_url": "https://www.primelocation.com/for-sale/details/70860065/",
    "image_url": "https://lid.zoocdn.com/u/1024/768/cdda91899fb5772cdbaba05035387f7cec18fa12.jpg",
    "postcode": "",
    "city": "Portsmouth",
    "monthly_rent": 330,
    "annual_rent": 3960,
    "gross_yield": 0.5,
    "area_sqm": null,
    "area_estimated": false,
    "london_borough": null,
    "london_district": null,
    "postcode_district": null,
    "postcode_area": null,
    "article4_area": false,
    "article4_status": "None",
    "property_category": "residential",
    "property_type": "unknown",
    "flat_floor": null,
    "has_garden": false,
    "has_parking": false,
    "property_age": null,
    "hmo_candidate": false,
    "migrated_at": "2025-08-12T15:23:03.087527"
  },
  {
    "address": "3 bed town house for sale Old Portsmouth, Hampshire PO1",
    "price": 715000,
    "bedrooms": 3,
    "bathrooms": 2,
    "description": "3-bed property in Portsmouth.",
    "property_url": "https://www.primelocation.com/for-sale/details/69397186/",
    "image_url": "https://lid.zoocdn.com/u/1024/768/e9e6c4e055f084595c9dd4f877e1971979fcf47c.jpg",
    "postcode": "",
    "city": "Portsmouth",
    "monthly_rent": 330,
    "annual_rent": 3960,
    "gross_yield": 0.55,
    "area_sqm": null,
    "area_estimated": false,
    "london_borough": null,
    "london_district": null,
    "postcode_district": null,
    "postcode_area": null,
    "article4_area": false,
    "article4_status": "None",
    "property_category": "residential",
    "property_type": "unknown",
    "flat_floor": null,
    "has_garden": false,
    "has_parking": false,
    "property_age": null,
    "hmo_candidate": false,
    "migrated_at": "2025-08-12T15:23:03.087572"
  },
  {
    "address": "4 bed detached house for sale Drayton, Hampshire PO6",
    "price": 950000,
    "bedrooms": 4,
    "bathrooms": 2,
    "description": "4-bed property in Portsmouth.",
    "property_url": "https://www.primelocation.com/for-sale/details/70981383/",
    "image_url": "https://lid.zoocdn.com/u/1024/768/9ed06310dc92b5d8df722381be421237c6d73d8c.jpg",
    "postcode": "",
    "city": "Portsmouth",
    "monthly_rent": 440,
    "annual_rent": 5280,
    "gross_yield": 0.56,
    "area_sqm": null,
    "area_estimated": false,
    "london_borough": null,
    "london_district": null,
    "postcode_district": null,
    "postcode_area": null,
    "article4_area": false,
    "article4_status": "None",
    "property_category": "residential",
    "property_type": "unknown",
    "flat_floor": null,
    "has_garden": false,
    "has_parking": false,
    "property_age": null,
    "hmo_candidate": false,
    "migrated_at": "2025-08-12T15:23:03.087593"
  },
  {
    "address": "2 bed flat for sale Oyster Quay, Port Solent PO6",
    "price": 750000,
    "bedrooms": 2,
    "bathrooms": 2,
    "description": "2-bed property in Portsmouth.",
    "property_url": "https://www.primelocation.com/for-sale/details/70356588/",
    "image_url": "https://lid.zoocdn.com/u/1024/768/fd90e89a847578c6320be7f73fcc5b2f8733f173.jpg",
    "postcode": "",
    "city": "Portsmouth",
    "monthly_rent": 220,
    "annual_rent": 2640,
    "gross_yield": 0.35,
    "area_sqm": null,
    "area_estimated": false,
    "london_borough": null,
    "london_district": null,
    "postcode_district": null,
    "postcode_area": null,
    "article4_area": false,
    "article4_status": "None",
    "property_category": "residential",
    "property_type": "unknown",
    "flat_floor": null,
    "has_garden": false,
    "has_parking": false,
    "property_age": null,
    "hmo_candidate": false,
    "migrated_at": "2025-08-12T15:23:03.087612"
  },
  {
    "address": "8 bed detached house for sale Drayton, Hampshire PO6",
    "price": 850000,
    "bedrooms": 8,
    "bathrooms": 3,
    "description": "8-bed property in Portsmouth.",
    "property_url": "https://www.primelocation.com/for-sale/details/65006178/",
    "image_url": "https://lid.zoocdn.com/u/1024/768/8ef75e4b412d80bc2a1c79d3ac0eb1ad8933f664.jpg",
    "postcode": "",
    "city": "Portsmouth",
    "monthly_rent": 880,
    "annual_rent": 10560,
    "gross_yield": 1.24,
    "area_sqm": null,
    "area_estimated": false,
    "london_borough": null,
    "london_district": null,
    "postcode_district": null,
    "postcode_area": null,
    "article4_area": false,
    "article4_status": "None",
    "property_category": "residential",
    "property_type": "unknown",
    "flat_floor": null,
    "has_garden": false,
    "has_parking": false,
    "property_age": null,
    "hmo_candidate": false,
    "migrated_at": "2025-08-12T15:23:03.087630"
  },
  {
    "address": "3 bed terraced house for sale Stanley Road, Stamshaw PO2",
    "price": 229995,
    "bedrooms": 3,
    "bathrooms": 1,
    "description": "3-bed property in Portsmouth.",
    "property_url": "https://www.primelocation.com/for-sale/details/66412957/",
    "image_url": "https://lid.zoocdn.com/u/1024/768/0f121ac06be0559c1933a95708084b0ca5f8da53.jpg",
    "postcode": "",
    "city": "Portsmouth",
    "monthly_rent": 330,
    "annual_rent": 3960,
    "gross_yield": 1.72,
    "area_sqm": null,
    "area_estimated": false,
    "london_borough": null,
    "london_district": null,
    "postcode_district": null,
    "postcode_area": null,
    "article4_area": false,
    "article4_status": "None",
    "property_category": "residential",
    "property_type": "unknown",
    "flat_floor": null,
    "has_garden": false,
    "has_parking": false,
    "property_age": null,
    "hmo_candidate": false,
    "migrated_at": "2025-08-12T15:23:03.087657"
  },
  {
    "address": "Land for sale London Road, Portsmouth PO2",
    "price": 900000,
    "bedrooms": 7,
    "bathrooms": 1,
    "description": "7-bed property in Portsmouth.",
    "property_url": "https://www.primelocation.com/for-sale/details/70376945/",
    "image_url": "https://lid.zoocdn.com/u/1024/768/ee1aabe4f16fbb1620f7094918d42230ef9b603e.jpg",
    "postcode": "",
    "city": "Portsmouth",
    "monthly_rent": 770,
    "annual_rent": 9240,
    "gross_yield": 1.03,
    "area_sqm": null,
    "area_estimated": false,
    "london_borough": null,
    "london_district": "Land for sale",
    "postcode_district": "PO2",
    "postcode_area": "PO",
    "article4_area": false,
    "article4_status": "None",
    "property_category": "residential",
    "property_type": "unknown",
    "flat_floor": null,
    "has_garden": false,
    "has_parking": false,
    "property_age": null,
    "hmo_candidate": false,
    "migrated_at": "2025-08-12T15:23:03.087725"
  },
  {
    "address": "3 bed town house for sale Grand Parade, Old Portsmouth PO1",
    "price": 950000,
    "bedrooms": 3,
    "bathrooms": 1,
    "description": "3-bed property in Portsmouth.",
    "property_url": "https://www.primelocation.com/for-sale/details/70983090/",
    "image_url": "https://lid.zoocdn.com/u/1024/768/8c9a1cfae686a84e00690c1bc830621afa26dc59.jpg",
    "postcode": "",
    "city": "Portsmouth",
    "monthly_rent": 330,
    "annual_rent": 3960,
    "gross_yield": 0.42,
    "area_sqm": null,
    "area_estimated": false,
    "london_borough": null,
    "london_district": null,
    "postcode_district": null,
    "postcode_area": null,
    "article4_area": false,
    "article4_status": "None",
    "property_category": "residential",
    "property_type": "unknown",
    "flat_floor": null,
    "has_garden": false,
    "has_parking": false,
    "property_age": null,
    "hmo_candidate": false,
    "migrated_at": "2025-08-12T15:23:03.087747"
  },
  {
    "address": "8 bed flat for sale Aylen Road, Portsmouth, Hampshire PO3",
    "price": 800000,
    "bedrooms": 8,
    "bathrooms": 4,
    "description": "8-bed property in Portsmouth.",
    "property_url": "https://www.primelocation.com/for-sale/details/68741441/",
    "image_url": "https://lid.zoocdn.com/u/1024/768/80193904d72a4a4b3c89af145f6c1c0ed971e471.jpg",
    "postcode": "",
    "city": "Portsmouth",
    "monthly_rent": 880,
    "annual_rent": 10560,
    "gross_yield": 1.32,
    "area_sqm": null,
    "area_estimated": false,
    "london_borough": null,
    "london_district": null,
    "postcode_district": null,
    "postcode_area": null,
    "article4_area": false,
    "article4_status": "None",
    "property_category": "residential",
    "property_type": "unknown",
    "flat_floor": null,
    "has_garden": false,
    "has_parking": false,
    "property_age": null,
    "hmo_candidate": false,
    "migrated_at": "2025-08-12T15:23:03.087767"
  },
  {
    "address": "3 bed detached house for sale Drayton, Hampshire PO6",
    "price": 800000,
    "bedrooms": 3,
    "bathrooms": 1,
    "description": "3-bed property in Portsmouth.",
    "property_url": "https://www.primelocation.com/for-sale/details/70484358/",
    "image_url": "https://lid.zoocdn.com/u/1024/768/322c0d3dcd44a66021f3d02ae19613f74ff94a70.jpg",
    "postcode": "",
    "city": "Portsmouth",
    "monthly_rent": 330,
    "annual_rent": 3960,
    "gross_yield": 0.5,
    "area_sqm": null,
    "area_estimated": false,
    "london_borough": null,
    "london_district": null,
    "postcode_district": null,
    "postcode_area": null,
    "article4_area": false,
    "article4_status": "None",
    "property_category": "residential",
    "property_type": "unknown",
    "flat_floor": null,
    "has_garden": false,
    "has_parking": false,
    "property_age": null,
    "hmo_candidate": false,
    "migrated_at": "2025-08-12T15:23:03.087787"
  },
  {
    "address": "4 bed detached house for sale Drayton, Hampshire PO6",
    "price": 975000,
    "bedrooms": 4,
    "bathrooms": 3,
    "description": "4-bed property in Portsmouth.",
    "property_url": "https://www.primelocation.com/for-sale/details/66762144/",
    "image_url": "https://lid.zoocdn.com/u/1024/768/f22fdabcee4745f153f8c9391db4aa8cf701da0e.jpg",
    "postcode": "",
    "city": "Portsmouth",
    "monthly_rent": 440,
    "annual_rent": 5280,
    "gross_yield": 0.54,
    "area_sqm": null,
    "area_estimated": false,
    "london_borough": null,
    "london_district": null,
    "postcode_district": null,
    "postcode_area": null,
    "article4_area": false,
    "article4_status": "None",
    "property_category": "residential",
    "property_type": "unknown",
    "flat_floor": null,
    "has_garden": false,
    "has_parking": false,
    "property_age": null,
    "hmo_candidate": false,
    "migrated_at": "2025-08-12T15:23:03.087806"
  },
  {
    "address": "4 bed detached house for sale Drayton, Hampshire PO6",
    "price": 750000,
    "bedrooms": 4,
    "bathrooms": 2,
    "description": "4-bed property in Portsmouth.",
    "property_url": "https://www.primelocation.com/for-sale/details/69585291/",
    "image_url": "https://lid.zoocdn.com/u/1024/768/eaa839ec35fb1fe5c3cd9b0ef374b3ff9d773988.jpg",
    "postcode": "",
    "city": "Portsmouth",
    "monthly_rent": 440,
    "annual_rent": 5280,
    "gross_yield": 0.7,
    "area_sqm": null,
    "area_estimated": false,
    "london_borough": null,
    "london_district": null,
    "postcode_district": null,
    "postcode_area": null,
    "article4_area": false,
    "article4_status": "None",
    "property_category": "residential",
    "property_type": "unknown",
    "flat_floor": null,
    "has_garden": false,
    "has_parking": false,
    "property_age": null,
    "hmo_candidate": false,
    "migrated_at": "2025-08-12T15:23:03.087828"
  },
  {
    "address": "4 bed detached house for sale Drayton, Hampshire PO6",
    "price": 850000,
    "bedrooms": 4,
    "bathrooms": 1,
    "description": "4-bed property in Portsmouth.",
    "property_url": "https://www.primelocation.com/for-sale/details/69792894/",
    "image_url": "https://lid.zoocdn.com/u/1024/768/3f702a9aa95f70bb60a3f1149dc45963b71a2c6d.jpg",
    "postcode": "",
    "city": "Portsmouth",
    "monthly_rent": 440,
    "annual_rent": 5280,
    "gross_yield": 0.62,
    "area_sqm": null,
    "area_estimated": false,
    "london_borough": null,
    "london_district": null,
    "postcode_district": null,
    "postcode_area": null,
    "article4_area": false,
    "article4_status": "None",
    "property_category": "residential",
    "property_type": "unknown",
    "flat_floor": null,
    "has_garden": false,
    "has_parking": false,
    "property_age": null,
    "hmo_candidate": false,
    "migrated_at": "2025-08-12T15:23:03.087848"
  },
  {
    "address": "4 bed town house for sale Carne Place, Port Solent, Portsmouth PO6",
    "price": 825000,
    "bedrooms": 4,
    "bathrooms": 3,
    "description": "4-bed property in Portsmouth.",
    "property_url": "https://www.primelocation.com/for-sale/details/66376384/",
    "image_url": "https://lid.zoocdn.com/u/1024/768/55fa0e66a88f24032d9917150e27807cf23b888c.jpg",
    "postcode": "",
    "city": "Portsmouth",
    "monthly_rent": 440,
    "annual_rent": 5280,
    "gross_yield": 0.64,
    "area_sqm": null,
    "area_estimated": false,
    "london_borough": null,
    "london_district": null,
    "postcode_district": null,
    "postcode_area": null,
    "article4_area": false,
    "article4_status": "None",
    "property_category": "residential",
    "property_type": "unknown",
    "flat_floor": null,
    "has_garden": false,
    "has_parking": false,
    "property_age": null,
    "hmo_candidate": false,
    "migrated_at": "2025-08-12T15:23:03.087868"
  },
  {
    "address": "5 bed property for sale Drayton Lane, Portsmouth PO6",
    "price": 925000,
    "bedrooms": 5,
    "bathrooms": 2,
    "description": "5-bed property in Portsmouth.",
    "property_url": "https://www.primelocation.com/for-sale/details/70791039/",
    "image_url": "https://lid.zoocdn.com/u/1024/768/0944542780349d00ec75f6689ce32954f9f5090b.jpg",
    "postcode": "",
    "city": "Portsmouth",
    "monthly_rent": 550,
    "annual_rent": 6600,
    "gross_yield": 0.71,
    "area_sqm": null,
    "area_estimated": false,
    "london_borough": null,
    "london_district": null,
    "postcode_district": null,
    "postcode_area": null,
    "article4_area": false,
    "article4_status": "None",
    "property_category": "residential",
    "property_type": "unknown",
    "flat_floor": null,
    "has_garden": false,
    "has_parking": false,
    "property_age": null,
    "hmo_candidate": false,
    "migrated_at": "2025-08-12T15:23:03.087887"
  },
  {
    "address": "4 bed property for sale Mulberry Lane, Drayton PO6",
    "price": 800000,
    "bedrooms": 4,
    "bathrooms": 1,
    "description": "4-bed property in Portsmouth.",
    "property_url": "https://www.primelocation.com/for-sale/details/70632773/",
    "image_url": "https://lid.zoocdn.com/u/1024/768/12c75e2dfeda26e8b7d1516174de6679055668c0.jpg",
    "postcode": "",
    "city": "Portsmouth",
    "monthly_rent": 440,
    "annual_rent": 5280,
    "gross_yield": 0.66,
    "area_sqm": null,
    "area_estimated": false,
    "london_borough": null,
    "london_district": null,
    "postcode_district": null,
    "postcode_area": null,
    "article4_area": false,
    "article4_status": "None",
    "property_category": "residential",
    "property_type": "unknown",
    "flat_floor": null,
    "has_garden": false,
    "has_parking": false,
    "property_age": null,
    "hmo_candidate": false,
    "migrated_at": "2025-08-12T15:23:03.087907"
  },
  {
    "address": "3 bed town house for sale Old Portsmouth, Hampshire PO1",
    "price": 750000,
    "bedrooms": 3,
    "bathrooms": 3,
    "description": "3-bed property in Portsmouth.",
    "property_url": "https://www.primelocation.com/for-sale/details/67799283/",
    "image_url": "https://lid.zoocdn.com/u/1024/768/c7309921077a7c14250bb5fcecbcceb58b7d90f4.jpg",
    "postcode": "",
    "city": "Portsmouth",
    "monthly_rent": 330,
    "annual_rent": 3960,
    "gross_yield": 0.53,
    "area_sqm": null,
    "area_estimated": false,
    "london_borough": null,
    "london_district": null,
    "postcode_district": null,
    "postcode_area": null,
    "article4_area": false,
    "article4_status": "None",
    "property_category": "residential",
    "property_type": "unknown",
    "flat_floor": null,
    "has_garden": false,
    "has_parking": false,
    "property_age": null,
    "hmo_candidate": false,
    "migrated_at": "2025-08-12T15:23:03.087952"
  }
]